molidb/__init__.py
molidb/my_module.py
molidb-0.1.7.dist-info/METADATA
molidb-0.1.7.dist-info/WHEEL
molidb-0.1.7.dist-info/top_level.txt
molidb-0.1.7.dist-info/RECORD
