Metadata-Version: 2.1
Name: molidb
Version: 0.1.7
Summary: A package for managing collections with AES encryption and compression
Home-page: https://github.com/fluffy-melli/MoliDB-pypi
Author: fluffy-melli
Author-email: yummyshibadog@gmail.com
License: MIT
Classifier: Programming Language :: Python :: 3
Classifier: License :: OSI Approved :: MIT License
Classifier: Operating System :: OS Independent
Requires-Python: >=3.6
Requires-Dist: requests
Requires-Dist: pycryptodome
Requires-Dist: python-dotenv
